fjord_kafka_migration
