Metadata-Version: 1.1
Name: fjord-kafka-migration
Version: 0.2.0
Summary: fjord kafka migration tools.
Home-page: UNKNOWN
Author: Tony Liu
Author-email: UNKNOWN
License: UNKNOWN
Keywords: fjord kafka migration tools built specific for aws environment.
Platform: UNKNOWN
Classifier: Development Status :: 4 - Beta
Classifier: Programming Language :: Python
Classifier: Programming Language :: Python :: 2.7
Classifier: Environment :: Console
Classifier: Intended Audience :: Developers
Classifier: Intended Audience :: System Administrators
Classifier: Operating System :: POSIX
Classifier: Operating System :: MacOS :: MacOS X
